latolog/__init__.py
latolog/main.py
logging_formatter/__init__.py
logging_formatter/format.py
utils/__init__.py
utils/constants.py
utils/types.py
LatoLog-0.1.2.dist-info/LICENSE
LatoLog-0.1.2.dist-info/METADATA
LatoLog-0.1.2.dist-info/WHEEL
LatoLog-0.1.2.dist-info/entry_points.txt
LatoLog-0.1.2.dist-info/top_level.txt
LatoLog-0.1.2.dist-info/RECORD
