Metadata-Version: 2.1
Name: LatoLog
Version: 0.1.2
Summary: A package that makes customizing logs easier than expected
Home-page: https://github.com/fabioqcorreia/LatoLog
Author: Fábio Correia
License: MIT
Platform: UNKNOWN
Classifier: Programming Language :: Python
Classifier: Programming Language :: Python :: 3
Classifier: License :: OSI Approved :: MIT License
Classifier: Operating System :: OS Independent
Requires-Python: >=3.6
